fast_vertex_quality_inference/__init__.py
fast_vertex_quality_inference/cli.py
fast_vertex_quality_inference/models/E_smear/configs.pkl
fast_vertex_quality_inference/models/E_smear/model.onnx
fast_vertex_quality_inference/models/E_smear/transfomer_quantiles.pkl
fast_vertex_quality_inference/models/PV/configs.pkl
fast_vertex_quality_inference/models/PV/model.onnx
fast_vertex_quality_inference/models/PV/transfomer_quantiles.pkl
fast_vertex_quality_inference/models/inheritance_2/configs.pkl
fast_vertex_quality_inference/models/inheritance_2/model.onnx
fast_vertex_quality_inference/models/inheritance_2/transfomer_quantiles.pkl
fast_vertex_quality_inference/models/inheritance_3/configs.pkl
fast_vertex_quality_inference/models/inheritance_3/model.onnx
fast_vertex_quality_inference/models/inheritance_3/transfomer_quantiles.pkl
fast_vertex_quality_inference/models/parent_2/configs.pkl
fast_vertex_quality_inference/models/parent_2/model.onnx
fast_vertex_quality_inference/models/parent_2/transfomer_quantiles.pkl
fast_vertex_quality_inference/models/parent_3/configs.pkl
fast_vertex_quality_inference/models/parent_3/model.onnx
fast_vertex_quality_inference/models/parent_3/transfomer_quantiles.pkl
fast_vertex_quality_inference/models/parent_4/configs.pkl
fast_vertex_quality_inference/models/parent_4/model.onnx
fast_vertex_quality_inference/models/parent_4/transfomer_quantiles.pkl
fast_vertex_quality_inference/network/run_network.py
fast_vertex_quality_inference/params.py
fast_vertex_quality_inference/pip_list.txt
fast_vertex_quality_inference/processing/data_manager.py
fast_vertex_quality_inference/processing/graph_network_manager.py
fast_vertex_quality_inference/processing/network_manager.py
fast_vertex_quality_inference/processing/processing_tools.py
fast_vertex_quality_inference/processing/transformers.py
fast_vertex_quality_inference/rapidsim/rapidsim_tools.py
fast_vertex_quality_inference/rapidsim/run_rapidsim.py
fast_vertex_quality_inference/runner.py
fast_vertex_quality_inference-1.0.15.dist-info/LICENSE.txt
fast_vertex_quality_inference-1.0.15.dist-info/METADATA
fast_vertex_quality_inference-1.0.15.dist-info/WHEEL
fast_vertex_quality_inference-1.0.15.dist-info/entry_points.txt
fast_vertex_quality_inference-1.0.15.dist-info/RECORD
