Metadata-Version: 2.1
Name: fast_vertex_quality_inference
Version: 1.0.15
Summary: Inference code for fast generation of vertex quality variables
Home-page: https://gitlab.cern.ch/amarshal/fast_vertexing_variables/-/tree/master/inference
License: MIT
Keywords: inference,vertex-quality,fast-generation
Author: Alex Marshall
Author-email: alex.marshall@bristol.ac.uk
Requires-Python: >=3.9,<4.0
Classifier: License :: OSI Approved :: MIT License
Classifier: Operating System :: OS Independent
Classifier: Programming Language :: Python :: 3
Classifier: Programming Language :: Python :: 3.9
Classifier: Programming Language :: Python :: 3.10
Classifier: Programming Language :: Python :: 3.11
Classifier: Programming Language :: Python :: 3.12
Classifier: Programming Language :: Python :: 3.13
Requires-Dist: awkward-pandas
Requires-Dist: dill
Requires-Dist: matplotlib
Requires-Dist: onnxruntime
Requires-Dist: pandas
Requires-Dist: pydantic
Requires-Dist: rich
Requires-Dist: scikit-learn
Requires-Dist: termcolor
Requires-Dist: typer
Requires-Dist: uproot
Requires-Dist: vector (==0.8.0)
